esds_spec/__init__.py
esds_spec/py.typed
esds_spec-0.1.0.dist-info/LICENSE
esds_spec-0.1.0.dist-info/METADATA
esds_spec-0.1.0.dist-info/WHEEL
esds_spec-0.1.0.dist-info/top_level.txt
esds_spec-0.1.0.dist-info/RECORD
